pydantic_openapi_ng/__init__.py
pydantic_openapi_ng/camel_case.py
pydantic_openapi_ng/command_line.py
pydantic_openapi_ng/openapi_generator.py
pydantic_openapi_ng-0.2.1.dist-info/entry_points.txt
pydantic_openapi_ng-0.2.1.dist-info/LICENSE
pydantic_openapi_ng-0.2.1.dist-info/WHEEL
pydantic_openapi_ng-0.2.1.dist-info/METADATA
pydantic_openapi_ng-0.2.1.dist-info/RECORD
