Metadata-Version: 2.1
Name: pydantic-openapi-ng
Version: 0.2.1
Summary: Generate OpenAPI schema from pydantic models
License: GPL-3.0
Author: Yury Blagoveshchenskiy
Author-email: yurathestorm@gmail.com
Requires-Python: >=3.6,<4.0
Classifier: License :: OSI Approved :: GNU General Public License v3 (GPLv3)
Classifier: Programming Language :: Python :: 3
Classifier: Programming Language :: Python :: 3.6
Classifier: Programming Language :: Python :: 3.7
Classifier: Programming Language :: Python :: 3.8
Requires-Dist: inflection
Requires-Dist: pydantic
